pyapi_framework-0.0.1.data/data/LICENSE
pyapi_framework-0.0.1.data/data/README.md
pyapi_framework-0.0.1.data/data/VERSION
pyapi_framework-0.0.1.data/data/requirements.txt
src/main.py
src/routes.py
src/service_handler.py
pyapi_framework-0.0.1.dist-info/LICENSE
pyapi_framework-0.0.1.dist-info/METADATA
pyapi_framework-0.0.1.dist-info/WHEEL
pyapi_framework-0.0.1.dist-info/top_level.txt
pyapi_framework-0.0.1.dist-info/RECORD
