Metadata-Version: 2.1
Name: pyapi-framework
Version: 0.0.1
Summary: A simple python REST api framework.
Home-page: https://github.com/WMRamadan/pyapi-framework
Author: Wael Ramadan
Author-email: wamramadan@gmail.com
License: GPLv3
Platform: UNKNOWN
License-File: LICENSE
